marrydoc/__about__.py
marrydoc/__init__.py
marrydoc/__main__.py
marrydoc/_decorator.py
marrydoc/_docstring.py
marrydoc/_script.py
marrydoc/tests/__init__.py
marrydoc/tests/test_based_on.py
marrydoc/tests/test_cmdline.py
marrydoc/tests/test_copied_from.py
marrydoc/tests/test_inherit.py
marrydoc/tests/samples/__init__.py
marrydoc/tests/samples/based_on/__init__.py
marrydoc/tests/samples/based_on/diffs.py
marrydoc/tests/samples/based_on/no_diff.py
marrydoc/tests/samples/copied_from/__init__.py
marrydoc/tests/samples/copied_from/diffs.py
marrydoc/tests/samples/copied_from/no_diff.py
marrydoc-0.2.0.dist-info/DESCRIPTION.rst
marrydoc-0.2.0.dist-info/METADATA
marrydoc-0.2.0.dist-info/RECORD
marrydoc-0.2.0.dist-info/WHEEL
marrydoc-0.2.0.dist-info/entry_points.txt
marrydoc-0.2.0.dist-info/metadata.json
marrydoc-0.2.0.dist-info/top_level.txt
marrydoc-0.2.0.dist-info/zip-safe
